{
  "@mui/styles": {
    "package": "@mui/styles",
    "downloads": {
      "5.9.1": 19474,
      "5.2.0": 668,
      "5.0.1": 13914,
      "5.5.3": 21976,
      "5.6.0": 5618,
      "5.9.0": 14838,
      "5.0.0": 1681,
      "5.8.4": 23842,
      "5.1.0": 5253,
      "5.9.2": 21441,
      "5.6.1": 7183,
      "5.4.4": 9496,
      "5.3.0": 29578,
      "5.10.2": 9618,
      "5.0.0-rc.1": 602,
      "5.8.7": 15984,
      "5.4.1": 8996,
      "5.4.2": 12141,
      "5.2.1": 1984,
      "5.1.1": 5440,
      "5.6.2": 40032,
      "5.8.6": 15377,
      "5.2.3": 29015,
      "5.5.0": 11736,
      "5.9.3": 122882,
      "5.5.1": 23468,
      "5.2.2": 3829,
      "5.8.3": 15938,
      "5.8.0": 38203,
      "5.0.0-rc.0": 99,
      "5.0.2": 8061,
      "5.7.0": 16460
    }
  },
  "@mui/lab": {
    "package": "@mui/lab",
    "downloads": {
      "5.0.0-alpha.59": 8229,
      "5.0.0-alpha.81": 14992,
      "5.0.0-alpha.63": 7766,
      "5.0.0-alpha.55": 3698,
      "5.0.0-alpha.51": 5384,
      "5.0.0-alpha.71": 12221,
      "5.0.0-alpha.52": 227,
      "5.0.0-alpha.48": 1911,
      "5.0.0-alpha.61": 2909,
      "5.0.0-alpha.83": 17050,
      "5.0.0-alpha.75": 21376,
      "5.0.0-alpha.85": 15492,
      "5.0.0-alpha.86": 38362,
      "5.0.0-alpha.80": 14751,
      "5.0.0-alpha.45": 1022,
      "5.0.0-alpha.65": 17678,
      "5.0.0-alpha.89": 28136,
      "5.0.0-alpha.76": 8067,
      "5.0.0-alpha.54": 4652,
      "5.0.0-alpha.67": 13155,
      "5.0.0-alpha.82": 18907,
      "5.0.0-alpha.64": 8594,
      "5.0.0-alpha.46": 729,
      "5.0.0-alpha.95": 111298,
      "5.0.0-alpha.58": 5471,
      "5.0.0-alpha.47": 1531,
      "5.0.0-alpha.77": 9541,
      "5.0.0-alpha.78": 13519,
      "5.0.0-alpha.90": 16775,
      "5.0.0-alpha.94": 40236,
      "5.0.0-alpha.69": 7724,
      "5.0.0-alpha.84": 19464,
      "5.0.0-alpha.96": 10930,
      "5.0.0-alpha.53": 10144,
      "5.0.0-alpha.74": 16793,
      "5.0.0-alpha.93": 32491,
      "5.0.0-alpha.60": 4831,
      "5.0.0-alpha.68": 13121,
      "5.0.0-alpha.92": 26352,
      "5.0.0-alpha.62": 2684,
      "5.0.0-alpha.88": 19974,
      "5.0.0-alpha.70": 9272,
      "5.0.0-alpha.87": 15593,
      "5.0.0-alpha.66": 8218,
      "5.0.0-alpha.73": 11673,
      "5.0.0-alpha.56": 1901,
      "5.0.0-alpha.79": 9407,
      "5.0.0-alpha.91": 21450,
      "5.0.0-alpha.50": 5426,
      "5.0.0-alpha.72": 13036,
      "5.0.0-alpha.57": 1916,
      "5.0.0-alpha.49": 4231
    }
  },
  "@mui/x-data-grid": {
    "package": "@mui/x-data-grid",
    "downloads": {
      "5.2.1": 2916,
      "5.14.0": 11688,
      "5.12.2": 8859,
      "4.0.1": 2305,
      "5.15.2": 50127,
      "5.6.0": 2435,
      "5.9.0": 9811,
      "5.12.3": 26519,
      "5.12.0": 9987,
      "5.8.0": 7210,
      "5.15.0": 13687,
      "4.0.0": 5777,
      "5.0.0-beta.3": 338,
      "4.0.2": 17975,
      "5.6.1": 11686,
      "5.0.0-beta.1": 540,
      "5.12.1": 8027,
      "5.4.0": 2081,
      "5.3.0": 2038,
      "5.2.0": 1683,
      "5.0.1": 1195,
      "5.15.3": 35674,
      "5.0.0-beta.0": 13,
      "5.5.1": 8307,
      "5.0.0-beta.6": 691,
      "5.10.0": 20793,
      "5.0.0-beta.5": 1549,
      "5.11.1": 12890,
      "5.0.0-beta.2": 1019,
      "5.5.0": 1779,
      "5.0.0-beta.4": 807,
      "5.1.0": 1748,
      "5.2.2": 3979,
      "5.11.0": 11880,
      "5.13.0": 17318,
      "5.7.0": 6989,
      "5.13.1": 17994,
      "5.0.0": 446,
      "5.0.0-beta.7": 874,
      "5.15.1": 20411
    }
  },
  "@mui/codemod": {
    "package": "@mui/codemod",
    "downloads": {
      "5.5.0": 9,
      "5.0.1": 42,
      "5.4.4": 246,
      "5.0.0-rc.1": 59,
      "5.6.0": 58,
      "5.4.1": 2,
      "5.8.3": 10,
      "5.0.5": 627,
      "5.8.4": 155,
      "5.1.0": 14,
      "5.9.3": 1100,
      "5.8.1": 236,
      "5.7.0": 156,
      "5.0.0": 15,
      "5.0.0-rc.0": 2,
      "5.4.2": 61,
      "5.2.1": 54,
      "5.8.0": 4,
      "5.6.1": 528,
      "5.2.0": 25,
      "5.2.2": 925,
      "5.0.2": 329,
      "5.8.5": 111,
      "5.0.4": 137,
      "5.5.3": 14,
      "5.1.1": 27,
      "5.3.0": 269,
      "5.5.1": 73,
      "5.6.4": 109,
      "5.8.7": 1160,
      "5.0.3": 4
    }
  },
  "@mui/base": {
    "package": "@mui/base",
    "downloads": {
      "5.0.0-alpha.84": 39928,
      "5.0.0-alpha.76": 26416,
      "5.0.0-alpha.88": 66735,
      "5.0.0-alpha.80": 39916,
      "5.0.0-alpha.62": 7034,
      "5.0.0-alpha.60": 8646,
      "5.0.0-alpha.63": 13247,
      "5.0.0-alpha.92": 214111,
      "5.0.0-alpha.66": 20467,
      "5.0.0-alpha.93": 343350,
      "5.0.0-alpha.56": 9596,
      "5.0.0-alpha.75": 18686,
      "5.0.0-alpha.90": 66682,
      "5.0.0-alpha.73": 49717,
      "5.0.0-alpha.87": 50723,
      "5.0.0-alpha.72": 23462,
      "5.0.0-alpha.81": 41169,
      "5.0.0-alpha.83": 52385,
      "5.0.0-alpha.64": 20863,
      "5.0.0-alpha.79": 47434,
      "5.0.0-alpha.57": 3762,
      "5.0.0-alpha.74": 47167,
      "5.0.0-alpha.65": 24622,
      "5.0.0-alpha.86": 37741,
      "5.0.0-alpha.77": 47056,
      "5.0.0-alpha.55": 9330,
      "5.0.0-alpha.94": 38419,
      "5.0.0-alpha.71": 27007,
      "5.0.0-alpha.70": 25072,
      "5.0.0-alpha.89": 55792,
      "5.0.0-alpha.69": 38584,
      "5.0.0-alpha.67": 23867,
      "5.0.0-alpha.82": 49233,
      "5.0.0-alpha.61": 6075,
      "5.0.0-alpha.68": 28156,
      "5.0.0-alpha.78": 25296,
      "5.0.0-alpha.58": 10462,
      "5.0.0-alpha.59": 15115,
      "5.0.0-alpha.91": 77438,
      "5.0.0-alpha.85": 74178
    }
  },
  "@mui/x-data-grid-pro": {
    "package": "@mui/x-data-grid-pro",
    "downloads": {
      "5.13.0": 7601,
      "5.10.0": 2938,
      "5.7.0": 1818,
      "5.3.0": 287,
      "5.12.0": 2923,
      "5.6.0": 1102,
      "5.6.1": 3710,
      "5.2.2": 430,
      "5.15.1": 7133,
      "5.5.0": 115,
      "5.0.0-beta.4": 169,
      "5.0.0-beta.2": 187,
      "5.9.0": 2309,
      "5.5.1": 2744,
      "5.0.0-beta.7": 275,
      "5.0.1": 331,
      "5.12.1": 3403,
      "5.8.0": 1735,
      "5.13.1": 3733,
      "5.2.0": 526,
      "5.0.0": 324,
      "5.0.0-beta.0": 2,
      "5.11.0": 3565,
      "5.1.0": 250,
      "5.2.1": 522,
      "5.12.2": 2912,
      "5.0.0-beta.6": 5,
      "5.15.0": 5406,
      "5.14.0": 3155,
      "5.0.0-beta.5": 102,
      "5.4.0": 982,
      "4.0.1": 329,
      "5.0.0-beta.3": 62,
      "4.0.0": 944,
      "5.15.3": 9413,
      "5.12.3": 11737,
      "5.15.2": 19806,
      "4.0.2": 4180,
      "5.11.1": 5534,
      "5.0.0-beta.1": 92
    }
  },
  "@mui/material": {
    "package": "@mui/material",
    "downloads": {
      "5.6.2": 44594,
      "5.6.1": 23288,
      "5.0.3": 6505,
      "5.4.1": 18767,
      "5.0.1": 4160,
      "5.0.0-rc.0": 256,
      "5.1.1": 7821,
      "5.3.0": 22099,
      "5.10.1": 339380,
      "5.8.2": 45216,
      "5.9.1": 61498,
      "5.10.0": 118731,
      "5.2.1": 2735,
      "5.5.0": 23023,
      "5.4.4": 16892,
      "5.9.2": 69531,
      "5.2.3": 9908,
      "5.8.5": 33448,
      "5.4.0": 19534,
      "5.6.3": 22381,
      "5.8.4": 45338,
      "5.2.7": 10591,
      "5.4.3": 17838,
      "5.9.3": 84410,
      "5.8.6": 44092,
      "5.2.2": 8278,
      "5.3.1": 18077,
      "5.0.5": 652,
      "5.10.2": 38499,
      "5.8.0": 38197,
      "5.6.4": 41766,
      "5.5.1": 18423,
      "5.0.6": 15444,
      "5.0.4": 11594,
      "5.2.6": 6147,
      "5.9.0": 50523,
      "5.4.2": 14937,
      "5.8.1": 41509,
      "5.7.0": 33152,
      "5.0.0-rc.1": 1088,
      "5.2.4": 6468,
      "5.5.2": 46249,
      "5.6.0": 16308,
      "5.2.5": 5801,
      "5.0.0": 4978,
      "5.8.7": 54923,
      "5.1.0": 9417,
      "5.8.3": 36383,
      "5.0.2": 7539,
      "5.5.3": 38038,
      "5.2.0": 8719,
      "5.2.8": 17106
    }
  },
  "@mui/x-data-grid-premium": {
    "package": "@mui/x-data-grid-premium",
    "downloads": {
      "5.13.0": 1279,
      "5.15.1": 2166,
      "5.12.3": 2966,
      "5.15.0": 1443,
      "5.12.1": 405,
      "5.12.0": 542,
      "5.13.1": 470,
      "5.15.3": 3066,
      "5.11.0": 862,
      "5.12.2": 300,
      "5.14.0": 852,
      "5.11.1": 1689,
      "5.15.2": 3445
    }
  },
  "@mui/joy": {
    "package": "@mui/joy",
    "downloads": {
      "5.0.0-alpha.37": 84,
      "5.0.0-alpha.0": 2,
      "5.0.0-alpha.35": 27,
      "5.0.0-alpha.11": 2,
      "5.0.0-alpha.10": 2,
      "5.0.0-alpha.18": 2,
      "5.0.0-alpha.3": 2,
      "5.0.0-alpha.34": 109,
      "5.0.0-alpha.9": 2,
      "5.0.0-alpha.22": 2,
      "5.0.0-alpha.31": 4,
      "5.0.0-alpha.6": 2,
      "5.0.0-alpha.40": 912,
      "5.0.0-alpha.39": 612,
      "5.0.0-alpha.33": 12,
      "5.0.0-alpha.24": 3,
      "5.0.0-alpha.12": 2,
      "5.0.0-alpha.42": 172,
      "5.0.0-alpha.29": 2,
      "5.0.0-alpha.1": 2,
      "5.0.0-alpha.23": 2,
      "5.0.0-alpha.30": 2,
      "5.0.0-alpha.36": 154,
      "5.0.0-alpha.19": 2,
      "5.0.0-alpha.8": 2,
      "5.0.0-alpha.5": 2,
      "5.0.0-alpha.38": 140,
      "5.0.0-alpha.32": 26,
      "5.0.0-alpha.20": 2,
      "5.0.0-alpha.15": 2,
      "5.0.0-alpha.13": 2,
      "5.0.0-alpha.28": 2,
      "5.0.0-alpha.14": 24,
      "5.0.0-alpha.21": 2,
      "5.0.0-alpha.7": 2,
      "5.0.0-alpha.25": 2,
      "5.0.0-alpha.27": 2,
      "5.0.0-alpha.17": 2,
      "5.0.0-alpha.26": 2,
      "5.0.0-alpha.2": 2,
      "5.0.0-alpha.16": 2,
      "5.0.0-alpha.4": 2,
      "5.0.0-alpha.41": 1582
    }
  },
  "@mui/system": {
    "package": "@mui/system",
    "downloads": {
      "5.0.2": 6680,
      "5.8.0": 38134,
      "5.9.1": 63094,
      "5.6.3": 23502,
      "5.2.8": 13884,
      "5.8.4": 66068,
      "5.6.0": 16538,
      "5.9.0": 55545,
      "5.0.6": 13365,
      "5.4.1": 19079,
      "5.7.0": 37818,
      "5.0.3": 5128,
      "5.0.0-rc.0": 1234,
      "5.5.2": 26383,
      "5.0.0-rc.1": 1294,
      "5.10.2": 40218,
      "5.4.3": 17236,
      "5.5.1": 22454,
      "5.9.3": 92285,
      "5.2.1": 2796,
      "5.5.3": 35616,
      "5.4.2": 12762,
      "5.2.5": 4701,
      "5.10.0": 125396,
      "5.0.1": 3845,
      "5.0.4": 8615,
      "5.9.2": 74524,
      "5.4.4": 16771,
      "5.8.2": 46002,
      "5.4.0": 20195,
      "5.2.3": 9310,
      "5.6.1": 26224,
      "5.8.3": 35848,
      "5.1.1": 6992,
      "5.5.0": 20622,
      "5.8.1": 42062,
      "5.0.0": 3383,
      "5.2.0": 8292,
      "5.10.1": 372769,
      "5.6.4": 43034,
      "5.8.6": 51924,
      "5.6.2": 44333,
      "5.2.2": 6961,
      "5.2.6": 16175,
      "5.2.4": 6309,
      "5.8.5": 34833,
      "5.1.0": 8213,
      "5.0.5": 525,
      "5.3.0": 32872,
      "5.8.7": 58913
    }
  },
  "@mui/icons-material": {
    "package": "@mui/icons-material",
    "downloads": {
      "5.0.0-rc.0": 208,
      "5.6.0": 12616,
      "5.5.0": 16920,
      "5.2.5": 32594,
      "5.3.1": 29130,
      "5.2.0": 17310,
      "5.1.0": 8118,
      "5.4.4": 12289,
      "5.8.3": 29293,
      "5.6.2": 113060,
      "5.1.1": 6127,
      "5.5.1": 96773,
      "5.0.3": 7321,
      "5.3.0": 16102,
      "5.0.0-rc.1": 944,
      "5.8.4": 661726,
      "5.0.5": 11137,
      "5.8.2": 31281,
      "5.6.1": 21710,
      "5.10.2": 29696,
      "5.4.1": 15597,
      "5.2.1": 11859,
      "5.0.4": 8488,
      "5.2.4": 6012,
      "5.8.0": 66830,
      "5.0.1": 9914,
      "5.4.2": 21877,
      "5.0.0": 4094
    }
  },
  "@mui/x-date-pickers": {
    "package": "@mui/x-date-pickers",
    "downloads": {
      "5.0.0-alpha.4": 12446,
      "5.0.0-beta.6": 53525,
      "5.0.0-alpha.6": 22548,
      "5.0.0-alpha.3": 10401,
      "5.0.0-beta.0": 19505,
      "5.0.0-alpha.1": 162935,
      "5.0.0-alpha.5": 16578,
      "5.0.0-alpha.0": 91460,
      "5.0.0-beta.4": 36284,
      "5.0.0-alpha.7": 34960,
      "5.0.0-beta.1": 20220,
      "5.0.0-beta.3": 24222,
      "5.0.0-beta.2": 24391,
      "5.0.0-beta.5": 70515,
      "5.0.0-alpha.2": 16008
    }
  },
  "@mui/styled-engine": {
    "package": "@mui/styled-engine",
    "downloads": {
      "5.7.0": 34563,
      "5.8.7": 326493,
      "5.4.2": 27398,
      "5.1.1": 6776,
      "5.6.1": 127541,
      "5.4.1": 19377,
      "5.10.1": 369643,
      "5.4.4": 55766,
      "5.0.2": 11277,
      "5.2.6": 27411,
      "5.5.2": 59220,
      "5.3.0": 48216,
      "5.0.0-rc.0": 1217,
      "5.6.0": 15860,
      "5.2.0": 25286,
      "5.2.5": 4735,
      "5.8.0": 296416,
      "5.0.1": 21061,
      "5.10.0": 123609,
      "5.1.0": 7786,
      "5.2.4": 5675,
      "5.10.2": 39902,
      "5.0.0": 3219,
      "5.0.0-rc.1": 1289
    }
  },
  "@mui/x-date-pickers-pro": {
    "package": "@mui/x-date-pickers-pro",
    "downloads": {
      "5.0.0-alpha.0": 418,
      "5.0.0-beta.4": 5831,
      "5.0.0-beta.1": 3025,
      "5.0.0-alpha.2": 1653,
      "5.0.0-beta.2": 2636,
      "5.0.0-alpha.4": 3103,
      "5.0.0-alpha.3": 1131,
      "5.0.0-beta.3": 2587,
      "5.0.0-beta.0": 2676,
      "5.0.0-alpha.7": 4057,
      "5.0.0-beta.6": 4320,
      "5.0.0-alpha.6": 2322,
      "5.0.0-alpha.1": 448,
      "5.0.0-alpha.5": 3880,
      "5.0.0-beta.5": 4933
    }
  }
}