{
  "@mui/icons-material": {
    "package": "@mui/icons-material",
    "downloads": {
      "5.10.16": 65364,
      "5.2.4": 3170,
      "5.4.1": 10526,
      "5.10.3": 63644,
      "5.0.4": 6110,
      "5.0.1": 5407,
      "5.10.14": 25052,
      "5.8.0": 34884,
      "5.10.15": 24668,
      "5.4.4": 7029,
      "5.2.0": 7481,
      "5.8.3": 13296,
      "5.6.2": 54487,
      "5.0.0-rc.1": 254,
      "5.0.3": 3534,
      "5.3.1": 14663,
      "5.3.0": 7483,
      "5.8.2": 12949,
      "5.11.0": 352117,
      "5.2.1": 9006,
      "5.1.1": 5004,
      "5.2.5": 24919,
      "5.5.0": 9465,
      "5.10.6": 53621,
      "5.11.11": 635208,
      "5.5.1": 46639,
      "5.0.0": 3769,
      "5.4.2": 13442,
      "5.1.0": 5009,
      "5.11.9": 113481,
      "5.6.1": 6750,
      "5.0.5": 5273,
      "5.8.4": 148970,
      "5.0.0-rc.0": 118,
      "5.6.0": 10958,
      "5.10.2": 13304,
      "5.10.9": 119701
    }
  },
  "@mui/joy": {
    "package": "@mui/joy",
    "downloads": {
      "5.0.0-alpha.39": 75,
      "5.0.0-alpha.57": 169,
      "5.0.0-alpha.43": 13,
      "5.0.0-alpha.41": 2172,
      "5.0.0-alpha.16": 4,
      "5.0.0-alpha.48": 34,
      "5.0.0-alpha.13": 3,
      "5.0.0-alpha.15": 2,
      "5.0.0-alpha.53": 87,
      "5.0.0-alpha.72": 7328,
      "5.0.0-alpha.2": 2,
      "5.0.0-alpha.42": 148,
      "5.0.0-alpha.4": 2,
      "5.0.0-alpha.49": 130,
      "5.0.0-alpha.50": 82,
      "5.0.0-alpha.70": 1249,
      "5.0.0-alpha.64": 1259,
      "5.0.0-alpha.55": 96,
      "5.0.0-alpha.22": 2,
      "5.0.0-alpha.51": 474,
      "5.0.0-alpha.9": 2,
      "5.0.0-alpha.54": 505,
      "5.0.0-alpha.10": 3,
      "5.0.0-alpha.18": 2,
      "5.0.0-alpha.34": 3,
      "5.0.0-alpha.24": 4,
      "5.0.0-alpha.33": 9,
      "5.0.0-alpha.6": 2,
      "5.0.0-alpha.31": 2,
      "5.0.0-alpha.23": 2,
      "5.0.0-alpha.30": 2,
      "5.0.0-alpha.45": 41,
      "5.0.0-alpha.71": 2410,
      "5.0.0-alpha.60": 145,
      "5.0.0-alpha.32": 2,
      "5.0.0-alpha.62": 779,
      "5.0.0-alpha.66": 1550,
      "5.0.0-alpha.0": 3,
      "5.0.0-alpha.19": 2,
      "5.0.0-alpha.8": 2,
      "5.0.0-alpha.59": 255,
      "5.0.0-alpha.37": 31,
      "5.0.0-alpha.28": 2,
      "5.0.0-alpha.67": 430,
      "5.0.0-alpha.46": 41,
      "5.0.0-alpha.27": 2,
      "5.0.0-alpha.12": 2,
      "5.0.0-alpha.65": 666,
      "5.0.0-alpha.38": 61,
      "5.0.0-alpha.25": 3,
      "5.0.0-alpha.69": 1062,
      "5.0.0-alpha.5": 2,
      "5.0.0-alpha.36": 8,
      "5.0.0-alpha.58": 672,
      "5.0.0-alpha.44": 41,
      "5.0.0-alpha.56": 877,
      "5.0.0-alpha.26": 4,
      "5.0.0-alpha.52": 157,
      "5.0.0-alpha.63": 389,
      "5.0.0-alpha.47": 42,
      "5.0.0-alpha.29": 3,
      "5.0.0-alpha.73": 532,
      "5.0.0-alpha.3": 2,
      "5.0.0-alpha.40": 19,
      "5.0.0-alpha.1": 2,
      "5.0.0-alpha.20": 2,
      "5.0.0-alpha.61": 339,
      "5.0.0-alpha.35": 4,
      "5.0.0-alpha.68": 891,
      "5.0.0-alpha.11": 3,
      "5.0.0-alpha.14": 2,
      "5.0.0-alpha.17": 3,
      "5.0.0-alpha.7": 2,
      "5.0.0-alpha.21": 2
    }
  },
  "@mui/x-data-grid-pro": {
    "package": "@mui/x-data-grid-pro",
    "downloads": {
      "5.17.12": 2906,
      "4.0.0": 752,
      "5.17.21": 2881,
      "5.12.2": 2374,
      "6.0.0-beta.0": 3,
      "5.17.26": 33190,
      "5.12.3": 2866,
      "6.0.0-beta.4": 374,
      "6.0.0-alpha.8": 2,
      "5.1.0": 480,
      "6.0.0-beta.2": 151,
      "5.11.1": 1028,
      "6.0.0-alpha.13": 8,
      "5.15.2": 2064,
      "4.0.2": 5796,
      "5.17.22": 2958,
      "6.0.0-alpha.4": 19,
      "5.13.1": 1668,
      "5.12.0": 1298,
      "5.6.0": 1461,
      "5.17.6": 2069,
      "5.17.15": 5485,
      "5.17.25": 17515,
      "5.17.11": 5611,
      "5.0.0-beta.4": 86,
      "6.0.3": 6340,
      "6.0.0-alpha.14": 1026,
      "5.8.0": 612,
      "5.17.20": 6304,
      "5.17.16": 2964,
      "5.2.0": 485,
      "6.0.0-alpha.10": 2,
      "5.9.0": 773,
      "5.5.1": 1788,
      "5.0.0-beta.7": 98,
      "6.0.0-alpha.15": 39,
      "5.17.7": 1326,
      "5.12.1": 1459,
      "6.0.0-alpha.3": 3,
      "5.11.0": 673,
      "5.17.18": 5723,
      "5.17.1": 2533,
      "6.0.0-alpha.1": 2,
      "6.0.0-alpha.6": 3,
      "5.17.24": 6543,
      "5.16.0": 2850,
      "5.0.0-beta.6": 3,
      "6.0.0": 3508,
      "6.0.1": 3842,
      "5.17.0": 60,
      "6.0.0-alpha.9": 4,
      "5.0.0-beta.3": 53,
      "5.0.0-beta.5": 8,
      "6.0.2": 7450,
      "5.0.0-beta.0": 3,
      "5.0.0": 3,
      "5.17.8": 4685,
      "5.17.4": 1303,
      "6.0.0-beta.3": 10,
      "6.0.0-alpha.0": 6,
      "5.15.1": 764,
      "5.5.0": 33,
      "5.17.13": 2032,
      "4.0.1": 55,
      "5.15.0": 2114,
      "6.0.0-alpha.7": 3,
      "5.17.9": 1733,
      "5.17.19": 1884,
      "5.7.0": 1430,
      "5.3.0": 239,
      "5.2.2": 367,
      "6.0.0-alpha.2": 251,
      "5.17.3": 2605,
      "6.0.0-alpha.11": 142,
      "5.17.23": 5351,
      "5.10.0": 1538,
      "5.0.1": 316,
      "5.15.3": 3759,
      "5.0.0-beta.1": 3,
      "6.0.0-alpha.12": 136,
      "5.17.17": 3981,
      "5.0.0-beta.2": 109,
      "6.0.0-beta.1": 6,
      "6.0.0-alpha.5": 3,
      "5.17.5": 3388,
      "5.17.10": 3997,
      "5.13.0": 2798,
      "6.0.0-beta.5": 83,
      "5.2.1": 542,
      "5.6.1": 684,
      "5.17.2": 2352,
      "5.14.0": 995,
      "5.4.0": 376,
      "5.17.14": 2408
    }
  },
  "@mui/styles": {
    "package": "@mui/styles",
    "downloads": {
      "5.2.2": 3064,
      "5.0.0-rc.0": 91,
      "5.0.2": 3683,
      "5.7.0": 5592,
      "5.2.3": 20382,
      "5.8.0": 14421,
      "5.11.7": 23903,
      "5.9.3": 20562,
      "5.5.1": 15231,
      "5.10.9": 6204,
      "5.3.0": 15652,
      "5.6.1": 2555,
      "5.10.15": 10164,
      "5.8.7": 6866,
      "5.1.0": 3731,
      "5.11.11": 15034,
      "5.10.2": 6538,
      "5.11.13": 118789,
      "5.4.4": 4343,
      "5.2.0": 342,
      "5.0.1": 9564,
      "5.11.0": 16464,
      "5.4.2": 7159,
      "5.9.1": 5402,
      "5.10.10": 27024,
      "5.5.0": 7703,
      "5.10.7": 4529,
      "5.10.3": 20344,
      "5.11.2": 46919,
      "5.10.6": 5528,
      "5.11.12": 29741,
      "5.0.0-rc.1": 369,
      "5.9.2": 5643,
      "5.4.1": 6540,
      "5.10.8": 9333,
      "5.8.3": 6211,
      "5.6.0": 4522,
      "5.9.0": 3109,
      "5.11.9": 27863,
      "5.10.16": 22324,
      "5.10.14": 10214,
      "5.2.1": 1516,
      "5.1.1": 3289,
      "5.11.1": 7325,
      "5.0.0": 1752,
      "5.8.4": 12776,
      "5.6.2": 10877,
      "5.8.6": 5090,
      "5.5.3": 18069
    }
  },
  "@mui/x-data-grid": {
    "package": "@mui/x-data-grid",
    "downloads": {
      "6.0.0-alpha.8": 2,
      "5.2.2": 2704,
      "6.0.0-beta.5": 429,
      "5.13.1": 11461,
      "5.0.0": 103,
      "5.17.3": 4517,
      "5.17.24": 17835,
      "6.0.0-alpha.14": 1033,
      "6.0.3": 25804,
      "5.17.25": 32750,
      "5.17.11": 11683,
      "5.17.22": 11074,
      "6.0.0-alpha.2": 253,
      "6.0.0-beta.1": 5,
      "5.1.0": 596,
      "6.0.0-alpha.5": 2,
      "5.7.0": 5992,
      "5.3.0": 988,
      "5.12.1": 3586,
      "5.4.0": 1033,
      "5.17.0": 244,
      "6.0.0-alpha.7": 2,
      "6.0.0-alpha.13": 40,
      "5.0.0-beta.3": 221,
      "5.6.1": 3827,
      "6.0.0-alpha.0": 8,
      "6.0.0-beta.0": 3,
      "4.0.2": 20753,
      "6.0.0-alpha.4": 19,
      "5.17.14": 25814,
      "5.17.1": 4306,
      "5.17.26": 100841,
      "5.17.13": 9487,
      "5.17.10": 8563,
      "5.17.4": 3403,
      "5.17.17": 15067,
      "5.0.0-beta.1": 626,
      "6.0.0-alpha.1": 2,
      "5.17.8": 10790,
      "5.17.18": 14828,
      "5.5.0": 1189,
      "6.0.0-beta.4": 394,
      "5.0.1": 873,
      "5.17.6": 6509,
      "6.0.0-alpha.15": 39,
      "6.0.0-alpha.11": 140,
      "5.2.1": 6118,
      "5.13.0": 5400,
      "5.11.0": 10612,
      "5.15.0": 3516,
      "5.12.0": 5870,
      "6.0.0-alpha.3": 3,
      "6.0.0-beta.3": 13,
      "5.14.0": 4521,
      "5.0.0-beta.6": 421,
      "5.10.0": 12408,
      "5.5.1": 4565,
      "5.15.2": 7994,
      "5.6.0": 2490,
      "6.0.0-alpha.6": 11,
      "5.0.0-beta.4": 217,
      "6.0.0-alpha.10": 3,
      "6.0.0": 8490,
      "5.17.21": 9590,
      "5.12.3": 7656,
      "5.17.2": 5934,
      "6.0.0-alpha.12": 134,
      "6.0.0-alpha.9": 32,
      "5.17.12": 8031,
      "5.17.9": 7211,
      "5.0.0-beta.2": 703,
      "5.17.23": 16904,
      "5.15.3": 6494,
      "5.16.0": 6827,
      "5.17.16": 8774,
      "5.17.19": 5978,
      "5.17.7": 4253,
      "6.0.2": 23962,
      "5.0.0-beta.7": 408,
      "5.9.0": 8179,
      "4.0.0": 3831,
      "5.15.1": 2749,
      "5.2.0": 1333,
      "5.17.20": 20015,
      "5.8.0": 4346,
      "5.0.0-beta.0": 4,
      "5.12.2": 4517,
      "4.0.1": 1893,
      "6.0.1": 18397,
      "5.0.0-beta.5": 1164,
      "5.17.5": 6511,
      "6.0.0-beta.2": 149,
      "5.11.1": 7271
    }
  },
  "@mui/x-date-pickers-pro": {
    "package": "@mui/x-date-pickers-pro",
    "downloads": {
      "5.0.0-beta.7": 1257,
      "6.0.0-alpha.4": 18,
      "6.0.0-alpha.10": 2,
      "5.0.0": 468,
      "5.0.20": 24468,
      "5.0.4": 3942,
      "5.0.0-alpha.2": 388,
      "6.0.0-alpha.6": 3,
      "6.0.0": 1063,
      "5.0.0-beta.3": 1024,
      "6.0.0-alpha.0": 2,
      "5.0.0-beta.2": 989,
      "5.0.15": 2407,
      "5.0.0-beta.0": 891,
      "5.0.14": 1412,
      "5.0.9": 3400,
      "5.0.13": 1785,
      "5.0.19": 4258,
      "6.0.0-alpha.8": 2,
      "6.0.0-beta.1": 5,
      "5.0.16": 1476,
      "6.0.2": 3779,
      "6.0.0-beta.3": 56,
      "5.0.2": 987,
      "6.0.0-alpha.5": 2,
      "5.0.0-alpha.5": 1405,
      "6.0.0-alpha.7": 2,
      "5.0.18": 2813,
      "6.0.0-beta.0": 309,
      "6.0.0-alpha.15": 148,
      "5.0.0-alpha.3": 202,
      "6.0.0-alpha.12": 3,
      "5.0.7": 940,
      "6.0.0-beta.5": 74,
      "5.0.1": 3033,
      "5.0.17": 1875,
      "5.0.0-alpha.1": 325,
      "5.0.0-beta.4": 315,
      "5.0.10": 3194,
      "6.0.0-alpha.3": 2,
      "5.0.8": 4079,
      "5.0.0-beta.5": 1808,
      "5.0.12": 2728,
      "6.0.1": 3245,
      "5.0.0-alpha.6": 1715,
      "6.0.0-alpha.1": 7,
      "5.0.6": 913,
      "6.0.0-beta.2": 98,
      "5.0.5": 2704,
      "6.0.3": 2842,
      "6.0.0-alpha.14": 935,
      "6.0.0-beta.4": 336,
      "5.0.0-alpha.7": 1888,
      "5.0.11": 1716,
      "6.0.0-alpha.13": 2,
      "5.0.0-alpha.0": 66,
      "6.0.0-alpha.11": 8,
      "5.0.3": 1900,
      "5.0.0-beta.6": 1077,
      "5.0.0-alpha.4": 315,
      "6.0.0-alpha.9": 3,
      "6.0.0-alpha.2": 2,
      "5.0.0-beta.1": 964
    }
  },
  "@mui/system": {
    "package": "@mui/system",
    "downloads": {
      "5.11.11": 88611,
      "5.1.1": 4353,
      "5.2.3": 4405,
      "5.8.7": 18674,
      "5.1.0": 3563,
      "5.8.5": 11240,
      "5.3.0": 14119,
      "5.11.7": 63625,
      "5.11.15": 38850,
      "5.0.5": 691,
      "5.2.6": 15815,
      "5.2.4": 3863,
      "5.10.1": 27908,
      "5.10.0": 22520,
      "5.11.14": 531634,
      "5.0.6": 5427,
      "5.4.3": 12947,
      "5.9.3": 31330,
      "5.5.1": 14373,
      "5.5.3": 27534,
      "5.11.4": 62593,
      "5.11.13": 189039,
      "5.7.0": 14399,
      "5.11.5": 110270,
      "5.10.3": 34751,
      "5.9.2": 21244,
      "5.10.16": 50670,
      "5.10.14": 34732,
      "5.8.2": 13690,
      "5.0.1": 1673,
      "5.0.4": 4077,
      "5.9.1": 17553,
      "5.11.2": 65074,
      "5.10.6": 22158,
      "5.8.6": 17778,
      "5.0.0-rc.1": 1042,
      "5.10.7": 24542,
      "5.10.5": 19982,
      "5.5.2": 15994,
      "5.4.4": 14422,
      "5.6.3": 10256,
      "5.11.8": 77720,
      "5.5.0": 7129,
      "5.11.12": 143606,
      "5.4.0": 7638,
      "5.10.4": 21360,
      "5.10.2": 17418,
      "5.11.0": 58782,
      "5.2.8": 7527,
      "5.8.4": 22333,
      "5.6.2": 20440,
      "5.10.15": 30365,
      "5.6.0": 8533,
      "5.9.0": 18632,
      "5.11.1": 26601,
      "5.0.0": 2828,
      "5.8.1": 20350,
      "5.2.1": 1896,
      "5.10.17": 46984,
      "5.10.13": 37275,
      "5.2.5": 2565,
      "5.10.10": 60877,
      "5.2.2": 4138,
      "5.10.12": 28028,
      "5.4.2": 5470,
      "5.10.8": 30380,
      "5.8.3": 15080,
      "5.10.9": 36657,
      "5.8.0": 16905,
      "5.0.2": 4829,
      "5.6.1": 8477,
      "5.11.9": 158922,
      "5.4.1": 15722,
      "5.0.0-rc.0": 1435,
      "5.0.3": 2597,
      "5.2.0": 2079,
      "5.6.4": 17686
    }
  },
  "@mui/x-date-pickers": {
    "package": "@mui/x-date-pickers",
    "downloads": {
      "5.0.5": 14439,
      "5.0.0-beta.5": 16838,
      "5.0.0-beta.2": 7156,
      "5.0.15": 24126,
      "5.0.0-beta.1": 7391,
      "5.0.13": 25397,
      "6.0.0-alpha.13": 327,
      "6.0.0-alpha.15": 286,
      "5.0.10": 24041,
      "6.0.3": 29940,
      "6.0.0-alpha.4": 17,
      "6.0.0-beta.3": 3115,
      "5.0.11": 20029,
      "5.0.0-alpha.0": 51367,
      "6.0.0-alpha.3": 6,
      "5.0.7": 9058,
      "5.0.3": 15954,
      "5.0.0-alpha.3": 5190,
      "5.0.0-beta.0": 9597,
      "6.0.0-alpha.7": 72,
      "6.0.0-alpha.1": 14,
      "5.0.0-beta.6": 9844,
      "5.0.18": 24999,
      "5.0.0-alpha.7": 13948,
      "6.0.0-beta.1": 18,
      "6.0.0-alpha.9": 3,
      "6.0.0-alpha.14": 941,
      "5.0.0": 9663,
      "6.0.2": 34747,
      "5.0.20": 234048,
      "6.0.0-alpha.0": 199,
      "5.0.6": 10353,
      "5.0.19": 26877,
      "5.0.0-alpha.6": 10991,
      "6.0.0-alpha.2": 5,
      "6.0.0-alpha.6": 24,
      "5.0.9": 27386,
      "6.0.0-beta.4": 893,
      "5.0.2": 9860,
      "5.0.0-alpha.4": 6200,
      "5.0.0-beta.3": 10545,
      "6.0.0-beta.5": 385,
      "5.0.0-beta.4": 11305,
      "5.0.8": 29258,
      "6.0.0-alpha.11": 9,
      "5.0.4": 26015,
      "6.0.0-beta.2": 157,
      "6.0.0-alpha.8": 2,
      "6.0.0": 13200,
      "5.0.0-alpha.2": 6098,
      "5.0.16": 20769,
      "6.0.0-beta.0": 311,
      "5.0.0-alpha.5": 6822,
      "5.0.1": 11132,
      "5.0.0-beta.7": 12988,
      "5.0.0-alpha.1": 67596,
      "6.0.0-alpha.12": 8,
      "6.0.1": 18827,
      "6.0.0-alpha.5": 2,
      "6.0.0-alpha.10": 2,
      "5.0.12": 16841,
      "5.0.17": 31036,
      "5.0.14": 14289
    }
  },
  "@mui/x-data-grid-premium": {
    "package": "@mui/x-data-grid-premium",
    "downloads": {
      "5.17.16": 909,
      "6.0.0-beta.1": 116,
      "6.0.0-alpha.2": 253,
      "5.17.21": 757,
      "5.13.1": 250,
      "5.17.15": 1286,
      "5.17.0": 26,
      "6.0.0-beta.3": 117,
      "5.17.4": 401,
      "6.0.0-beta.5": 66,
      "5.12.0": 391,
      "6.0.0-alpha.13": 116,
      "6.0.0-alpha.10": 113,
      "5.17.20": 2089,
      "6.0.0-alpha.0": 117,
      "5.17.5": 1002,
      "6.0.0-alpha.14": 1128,
      "6.0.0-alpha.12": 113,
      "5.17.17": 382,
      "5.17.12": 367,
      "6.0.0-alpha.6": 114,
      "6.0.0": 1056,
      "5.15.3": 887,
      "6.0.0-alpha.8": 114,
      "5.17.22": 317,
      "5.17.2": 556,
      "6.0.0-beta.4": 5,
      "5.11.1": 317,
      "6.0.0-beta.2": 182,
      "5.12.2": 347,
      "5.12.1": 191,
      "6.0.0-alpha.4": 113,
      "6.0.0-alpha.11": 252,
      "5.17.26": 10462,
      "5.17.6": 1115,
      "6.0.0-alpha.15": 118,
      "5.17.9": 734,
      "5.17.3": 1327,
      "5.11.0": 239,
      "6.0.0-alpha.7": 113,
      "5.17.11": 877,
      "5.17.25": 1765,
      "5.12.3": 525,
      "5.16.0": 282,
      "6.0.0-alpha.5": 113,
      "6.0.1": 2484,
      "5.14.0": 509,
      "6.0.0-alpha.3": 113,
      "5.17.1": 176,
      "6.0.3": 1882,
      "5.17.23": 974,
      "5.15.2": 335,
      "5.15.1": 401,
      "6.0.0-beta.0": 113,
      "6.0.0-alpha.1": 113,
      "5.17.7": 609,
      "6.0.2": 2045,
      "5.17.13": 742,
      "5.13.0": 395,
      "5.17.14": 762,
      "5.17.8": 2496,
      "6.0.0-alpha.9": 117,
      "5.17.18": 957,
      "5.17.10": 1066,
      "5.17.24": 3448,
      "5.15.0": 786,
      "5.17.19": 260
    }
  },
  "@mui/material": {
    "package": "@mui/material",
    "downloads": {
      "5.5.3": 27929,
      "5.4.2": 9327,
      "5.11.1": 25954,
      "5.10.16": 47346,
      "5.0.6": 6372,
      "5.10.3": 38817,
      "5.10.14": 33200,
      "5.8.6": 19152,
      "5.10.12": 28745,
      "5.0.0-rc.0": 165,
      "5.0.1": 2411,
      "5.4.4": 10819,
      "5.9.2": 22953,
      "5.2.1": 2538,
      "5.10.13": 41147,
      "5.2.7": 12603,
      "5.8.4": 19537,
      "5.2.3": 5153,
      "5.10.17": 46437,
      "5.4.3": 13351,
      "5.11.8": 71613,
      "5.10.9": 35776,
      "5.5.1": 9978,
      "5.3.0": 9817,
      "5.9.3": 33599,
      "5.10.0": 22111,
      "5.8.2": 21665,
      "5.8.5": 12443,
      "5.7.0": 13726,
      "5.0.0-rc.1": 1057,
      "5.8.1": 22838,
      "5.10.4": 21913,
      "5.10.7": 21059,
      "5.11.15": 31925,
      "5.11.9": 53521,
      "5.6.4": 22233,
      "5.8.0": 17294,
      "5.11.12": 124303,
      "5.0.2": 4650,
      "5.8.3": 15727,
      "5.11.14": 468415,
      "5.9.0": 15179,
      "5.2.6": 3686,
      "5.10.8": 32645,
      "5.2.0": 2437,
      "5.6.1": 8189,
      "5.11.0": 68457,
      "5.10.6": 19210,
      "5.4.1": 10816,
      "5.2.5": 3491,
      "5.2.2": 5458,
      "5.3.1": 9516,
      "5.6.0": 9291,
      "5.10.15": 32296,
      "5.6.3": 8971,
      "5.4.0": 10307,
      "5.8.7": 20538,
      "5.2.4": 4116,
      "5.5.2": 16095,
      "5.0.3": 3498,
      "5.11.5": 40094,
      "5.1.0": 5602,
      "5.11.3": 40405,
      "5.11.11": 78872,
      "5.0.0": 5633,
      "5.10.5": 20524,
      "5.11.6": 55889,
      "5.11.7": 58389,
      "5.10.10": 31430,
      "5.11.2": 18265,
      "5.2.8": 7478,
      "5.5.0": 9529,
      "5.0.5": 724,
      "5.10.2": 17378,
      "5.1.1": 5584,
      "5.6.2": 13455,
      "5.0.4": 5850,
      "5.11.10": 101355,
      "5.10.1": 26146,
      "5.9.1": 16689,
      "5.11.13": 173632,
      "5.11.4": 61579,
      "5.10.11": 31200
    }
  },
  "@mui/codemod": {
    "package": "@mui/codemod",
    "downloads": {
      "5.8.7": 114,
      "5.5.1": 89,
      "5.6.4": 157,
      "5.5.3": 283,
      "5.11.5": 40,
      "5.11.9": 711,
      "5.3.0": 300,
      "5.11.7": 52,
      "5.7.0": 98,
      "5.10.11": 2,
      "5.10.4": 48,
      "5.1.0": 11,
      "5.8.1": 171,
      "5.9.3": 251,
      "5.8.4": 225,
      "5.0.5": 284,
      "5.11.0": 563,
      "5.0.0-rc.0": 3,
      "5.0.0": 3,
      "5.11.11": 174,
      "5.4.4": 2,
      "5.8.0": 2,
      "5.8.5": 44,
      "5.0.2": 3,
      "5.0.4": 6,
      "5.1.1": 81,
      "5.2.2": 540,
      "5.5.0": 3,
      "5.10.10": 2,
      "5.6.0": 64,
      "5.0.0-rc.1": 11,
      "5.10.5": 2,
      "5.10.7": 2,
      "5.4.2": 111,
      "5.2.1": 2,
      "5.10.14": 36,
      "5.8.3": 3,
      "5.10.8": 3,
      "5.11.6": 7,
      "5.10.12": 101,
      "5.10.3": 9,
      "5.11.12": 451,
      "5.10.17": 64,
      "5.4.1": 3,
      "5.0.3": 4,
      "5.11.14": 1133,
      "5.6.1": 22,
      "5.10.9": 16,
      "5.0.1": 2,
      "5.10.16": 72,
      "5.10.6": 38,
      "5.2.0": 21
    }
  },
  "@mui/base": {
    "package": "@mui/base",
    "downloads": {
      "5.0.0-alpha.83": 24543,
      "5.0.0-alpha.72": 13941,
      "5.0.0-alpha.81": 19647,
      "5.0.0-alpha.114": 48935,
      "5.0.0-alpha.78": 11097,
      "5.0.0-alpha.85": 27640,
      "5.0.0-alpha.70": 25000,
      "5.0.0-alpha.89": 17155,
      "5.0.0-alpha.77": 18737,
      "5.0.0-alpha.95": 40134,
      "5.0.0-alpha.115": 64657,
      "5.0.0-alpha.99": 24356,
      "5.0.0-alpha.73": 19335,
      "5.0.0-alpha.119": 207621,
      "5.0.0-alpha.111": 30307,
      "5.0.0-alpha.123": 32553,
      "5.0.0-alpha.101": 42045,
      "5.0.0-alpha.87": 22070,
      "5.0.0-alpha.79": 26130,
      "5.0.0-alpha.62": 4764,
      "5.0.0-alpha.120": 52814,
      "5.0.0-alpha.64": 11058,
      "5.0.0-alpha.118": 164767,
      "5.0.0-alpha.105": 42277,
      "5.0.0-alpha.86": 15063,
      "5.0.0-alpha.65": 12183,
      "5.0.0-alpha.121": 187022,
      "5.0.0-alpha.92": 62567,
      "5.0.0-alpha.100": 36986,
      "5.0.0-alpha.112": 64268,
      "5.0.0-alpha.108": 51568,
      "5.0.0-alpha.116": 66478,
      "5.0.0-alpha.66": 12361,
      "5.0.0-alpha.84": 18426,
      "5.0.0-alpha.93": 31765,
      "5.0.0-alpha.56": 3497,
      "5.0.0-alpha.88": 22710,
      "5.0.0-alpha.76": 9457,
      "5.0.0-alpha.71": 14135,
      "5.0.0-alpha.59": 8707,
      "5.0.0-alpha.104": 32943,
      "5.0.0-alpha.58": 6691,
      "5.0.0-alpha.107": 34845,
      "5.0.0-alpha.55": 7016,
      "5.0.0-alpha.94": 21064,
      "5.0.0-alpha.117": 78386,
      "5.0.0-alpha.98": 25002,
      "5.0.0-alpha.110": 71842,
      "5.0.0-alpha.96": 24972,
      "5.0.0-alpha.82": 30741,
      "5.0.0-alpha.122": 497799,
      "5.0.0-alpha.68": 19229,
      "5.0.0-alpha.61": 4306,
      "5.0.0-alpha.57": 3473,
      "5.0.0-alpha.91": 27030,
      "5.0.0-alpha.97": 26367,
      "5.0.0-alpha.90": 20595,
      "5.0.0-alpha.74": 37676,
      "5.0.0-alpha.75": 13089,
      "5.0.0-alpha.113": 66824,
      "5.0.0-alpha.106": 38996,
      "5.0.0-alpha.80": 15703,
      "5.0.0-alpha.67": 12976,
      "5.0.0-alpha.102": 36937,
      "5.0.0-alpha.69": 26285,
      "5.0.0-alpha.109": 51895,
      "5.0.0-alpha.103": 33699,
      "5.0.0-alpha.63": 14173,
      "5.0.0-alpha.60": 6351
    }
  },
  "@mui/lab": {
    "package": "@mui/lab",
    "downloads": {
      "5.0.0-alpha.64": 5943,
      "5.0.0-alpha.46": 690,
      "5.0.0-alpha.57": 1705,
      "5.0.0-alpha.123": 58019,
      "5.0.0-alpha.79": 4300,
      "5.0.0-alpha.98": 10948,
      "5.0.0-alpha.56": 1427,
      "5.0.0-alpha.50": 3452,
      "5.0.0-alpha.96": 7298,
      "5.0.0-alpha.112": 19012,
      "5.0.0-alpha.49": 3426,
      "5.0.0-alpha.78": 11203,
      "5.0.0-alpha.90": 4266,
      "5.0.0-alpha.94": 10437,
      "5.0.0-alpha.72": 8373,
      "5.0.0-alpha.66": 5506,
      "5.0.0-alpha.73": 8294,
      "5.0.0-alpha.117": 23420,
      "5.0.0-alpha.91": 8656,
      "5.0.0-alpha.108": 14218,
      "5.0.0-alpha.106": 10570,
      "5.0.0-alpha.76": 5066,
      "5.0.0-alpha.67": 8414,
      "5.0.0-alpha.54": 2389,
      "5.0.0-alpha.65": 7269,
      "5.0.0-alpha.82": 11155,
      "5.0.0-alpha.89": 7903,
      "5.0.0-alpha.116": 16861,
      "5.0.0-alpha.61": 2527,
      "5.0.0-alpha.45": 1292,
      "5.0.0-alpha.84": 7065,
      "5.0.0-alpha.52": 806,
      "5.0.0-alpha.115": 19207,
      "5.0.0-alpha.118": 23369,
      "5.0.0-alpha.121": 25639,
      "5.0.0-alpha.87": 4693,
      "5.0.0-alpha.88": 8196,
      "5.0.0-alpha.124": 153216,
      "5.0.0-alpha.119": 19211,
      "5.0.0-alpha.95": 17493,
      "5.0.0-alpha.104": 16210,
      "5.0.0-alpha.102": 13053,
      "5.0.0-alpha.59": 5154,
      "5.0.0-alpha.114": 19061,
      "5.0.0-alpha.111": 19445,
      "5.0.0-alpha.80": 8789,
      "5.0.0-alpha.63": 10351,
      "5.0.0-alpha.81": 5186,
      "5.0.0-alpha.120": 55929,
      "5.0.0-alpha.97": 11762,
      "5.0.0-alpha.68": 11120,
      "5.0.0-alpha.101": 6799,
      "5.0.0-alpha.93": 9198,
      "5.0.0-alpha.60": 4102,
      "5.0.0-alpha.70": 3926,
      "5.0.0-alpha.103": 16491,
      "5.0.0-alpha.77": 3673,
      "5.0.0-alpha.62": 1930,
      "5.0.0-alpha.105": 8625,
      "5.0.0-alpha.99": 10560,
      "5.0.0-alpha.100": 8626,
      "5.0.0-alpha.47": 1579,
      "5.0.0-alpha.58": 3576,
      "5.0.0-alpha.109": 9581,
      "5.0.0-alpha.110": 17763,
      "5.0.0-alpha.122": 47863,
      "5.0.0-alpha.69": 4451,
      "5.0.0-alpha.48": 1336,
      "5.0.0-alpha.92": 8502,
      "5.0.0-alpha.86": 12504,
      "5.0.0-alpha.55": 3116,
      "5.0.0-alpha.51": 4619,
      "5.0.0-alpha.71": 12359,
      "5.0.0-alpha.53": 4587,
      "5.0.0-alpha.74": 12382,
      "5.0.0-alpha.75": 17290,
      "5.0.0-alpha.85": 6009,
      "5.0.0-alpha.83": 8443,
      "5.0.0-alpha.107": 9108,
      "5.0.0-alpha.113": 11224
    }
  },
  "@mui/styled-engine": {
    "package": "@mui/styled-engine",
    "downloads": {
      "5.10.2": 14554,
      "5.0.0-rc.1": 1039,
      "5.11.9": 155887,
      "5.4.4": 33348,
      "5.10.8": 179293,
      "5.4.1": 10123,
      "5.6.1": 53357,
      "5.1.1": 4182,
      "5.11.0": 371244,
      "5.0.2": 4643,
      "5.10.7": 23998,
      "5.10.5": 19136,
      "5.0.0": 2696,
      "5.2.4": 2983,
      "5.10.3": 32328,
      "5.10.0": 20492,
      "5.5.2": 38145,
      "5.0.1": 12395,
      "5.2.5": 2750,
      "5.11.8": 73457,
      "5.10.14": 63771,
      "5.10.16": 89964,
      "5.1.0": 3213,
      "5.2.0": 11263,
      "5.8.7": 97169,
      "5.11.11": 904434,
      "5.10.1": 27310,
      "5.2.6": 21355,
      "5.7.0": 10833,
      "5.10.6": 21941,
      "5.10.4": 19833,
      "5.0.0-rc.0": 1382,
      "5.6.0": 7173,
      "5.3.0": 20422,
      "5.4.2": 16907,
      "5.8.0": 101050
    }
  }
}